little_dinosaur/__init__.py
little_dinosaur/confident_learning.py
little_dinosaur/confident_learning_model.py
little_dinosaur/data_augmentation.py
little_dinosaur/download_utils.py
little_dinosaur/eat.py
little_dinosaur/load_pre_model.py
little_dinosaur/nlp_classification_model.py
little_dinosaur/translate.py
little_dinosaur/utils.py
little_dinosaur-0.0.34.dist-info/METADATA
little_dinosaur-0.0.34.dist-info/WHEEL
little_dinosaur-0.0.34.dist-info/top_level.txt
little_dinosaur-0.0.34.dist-info/RECORD
