Metadata-Version: 2.1
Name: little-dinosaur
Version: 0.0.34
Summary: utils for nlp
Home-page: https://github.com/hgliyuhao
Author: liyuhao
Author-email: 1241225413@qq.com
License: Apache License 2.0
Platform: UNKNOWN
Requires-Dist: fairies
Requires-Dist: bert4keras
Requires-Dist: GitPython
Requires-Dist: numpy
Requires-Dist: synonyms
